{
  "appointments": [
    {
      "date": "2025-01-12",
      "title": "Meeting with John",
      "startTime": "10:00",
      "endTime": "11:00",
      "color": "blue",
      "id": "945c"
    },
    {
      "date": "2025-01-13",
      "title": "Lunch with Sarah",
      "startTime": "12:00",
      "endTime": "13:00",
      "color": "green",
      "id": "e5be"
    },
    {
      "id": "6f5e",
      "date": "2025-01-14T13:38:31.567Z",
      "title": "stydu",
      "startTime": "14:38",
      "endTime": "14:38"
    },
    {
      "id": "c98b",
      "date": "2025-01-14T13:48:06.259Z",
      "title": "do the laundry",
      "startTime": "14:48",
      "endTime": "14:48"
    },
    {
      "title": "do the asd asap",
      "date": "2025-01-06T23:00:00.000Z",
      "startTime": "14:54",
      "endTime": "14:54",
      "id": "4a24"
    },
    {
      "title": "sleep",
      "date": "2025-01-07T23:00:00.000Z",
      "startTime": "14:56",
      "endTime": "14:56",
      "id": "be0b"
    },
    {
      "id": "0ac5",
      "title": "be prod",
      "date": "2025-01-08T23:00:00.000Z",
      "startTime": "14:57",
      "endTime": "14:57"
    },
    {
      "id": "227b",
      "date": "2025-01-14T14:04:13.354Z",
      "title": "sth",
      "startTime": "15:04",
      "endTime": "15:04"
    },
    {
      "id": "7d77",
      "date": "2025-01-14T14:57:22.337Z",
      "title": "g",
      "startTime": "15:57",
      "endTime": "15:57"
    },
    {
      "id": "611b",
      "date": "2025-01-14T16:12:21.133Z",
      "title": "d o the ",
      "startTime": "17:12",
      "endTime": "17:12"
    },
    {
      "id": "73ed",
      "date": "2025-01-14T23:00:00.000Z",
      "title": "f",
      "startTime": "17:12",
      "endTime": "17:12"
    },
    {
      "id": "a64b",
      "date": "2025-01-14T16:12:54.693Z",
      "title": "f",
      "startTime": "17:12",
      "endTime": "17:12"
    },
    {
      "id": "e95c",
      "date": "2025-01-14T16:15:39.807Z",
      "title": "hello!!!",
      "startTime": "17:15",
      "endTime": "17:15"
    },
    {
      "id": "3cc4",
      "date": "2025-01-15T16:48:07.207Z",
      "title": "y",
      "startTime": "05:00",
      "endTime": "05:00"
    },
    {
      "id": "68bf",
      "date": "2025-01-14T23:00:00.000Z",
      "title": "i",
      "startTime": "17:00",
      "endTime": "17:00"
    }
  ]
}